hxy_lib/__init__.py
hxy_lib/analysis/__init__.py
hxy_lib/analysis/analysis_func.py
hxy_lib/bin/srtrans.exe
hxy_lib/plot/__init__.py
hxy_lib/plot/plot_func.py
hxy_lib/utils/__init__.py
hxy_lib/utils/dev_import_func.py
hxy_lib-0.2.43.dist-info/METADATA
hxy_lib-0.2.43.dist-info/WHEEL
hxy_lib-0.2.43.dist-info/top_level.txt
hxy_lib-0.2.43.dist-info/RECORD
